templatise/__init__.py
templatise/actions.py
templatise/configuration.py
templatise/git.py
templatise/initialise.py
templatise/licence.py
templatise/licenses.json
templatise/project_name.py
templatise-2.3.1.dist-info/LICENSE
templatise-2.3.1.dist-info/METADATA
templatise-2.3.1.dist-info/WHEEL
templatise-2.3.1.dist-info/entry_points.txt
templatise-2.3.1.dist-info/RECORD
