Metadata-Version: 2.1
Name: templatise
Version: 2.3.1
Summary: You can use template.py to create a new GitHub repository.
Home-page: https://github.com/alunduil/template.py
License: Unlicense
Keywords: python,template,vscode,devcontainers
Author: Alex Brandt
Author-email: alunduil@gmail.com
Requires-Python: >=3.9,<4.0
Classifier: Development Status :: 5 - Production/Stable
Classifier: Environment :: Console
Classifier: Intended Audience :: Developers
Classifier: License :: OSI Approved
Classifier: License :: OSI Approved :: The Unlicense (Unlicense)
Classifier: Operating System :: OS Independent
Classifier: Programming Language :: Python :: 3
Classifier: Programming Language :: Python :: 3.9
Classifier: Programming Language :: Python :: 3.10
Classifier: Programming Language :: Python :: 3.11
Classifier: Programming Language :: Python :: 3.12
Classifier: Programming Language :: Python :: 3.13
Classifier: Programming Language :: Python :: 3 :: Only
Classifier: Programming Language :: Python :: 3.7
Classifier: Programming Language :: Python :: 3.8
Classifier: Topic :: Software Development
Classifier: Topic :: System :: Installation/Setup
Classifier: Typing :: Typed
Requires-Dist: click (>=8.1.3,<9.0.0)
Requires-Dist: click-log (>=0.4.0,<0.5.0)
Requires-Dist: requests (>=2.28.1,<3.0.0)
Requires-Dist: retry (>=0.9.2,<0.10.0)
Requires-Dist: toml (>=0.10.2,<0.11.0)
Requires-Dist: toml-sort (>=0.23,<0.25)
Project-URL: Repository, https://github.com/alunduil/template.py
